sendfn/__init__.py
sendfn/client.py
sendfn/errors.py
sendfn/models.py
sendfn/database/__init__.py
sendfn/database/helpers.py
sendfn/database/memory.py
sendfn/email/__init__.py
sendfn/email/aws_ses.py
sendfn/email/provider.py
sendfn/email/service.py
sendfn/email/templates.py
sendfn/events/__init__.py
sendfn/events/tracker.py
sendfn/events/webhook_handler.py
sendfn/http/__init__.py
sendfn/http/fastapi.py
sendfn/http/routes.py
sendfn/push/__init__.py
sendfn/push/apns.py
sendfn/push/device_manager.py
sendfn/push/fcm.py
sendfn/push/provider.py
sendfn/push/service.py
sendfn/sms/__init__.py
sendfn/sms/console.py
sendfn/sms/provider.py
sendfn/sms/service.py
sendfn/suppression/__init__.py
sendfn/suppression/manager.py
sendfn-0.0.1.dist-info/METADATA
sendfn-0.0.1.dist-info/WHEEL
sendfn-0.0.1.dist-info/RECORD
