Metadata-Version: 2.4
Name: sendfn
Version: 0.0.1
Summary: Self-hosted communications platform SDK for email, push notifications, and SMS
Project-URL: Documentation, https://docs.superfunctions.dev/sendfn
Project-URL: Repository, https://github.com/21nCo/super-functions
Project-URL: Issues, https://github.com/21nCo/super-functions/issues
Author: 21n
License-Expression: MIT
Keywords: communications,email,notifications,push,sms,superfunctions
Classifier: Development Status :: 3 - Alpha
Classifier: Intended Audience :: Developers
Classifier: License :: OSI Approved :: MIT License
Classifier: Programming Language :: Python :: 3
Classifier: Programming Language :: Python :: 3.10
Classifier: Programming Language :: Python :: 3.11
Classifier: Programming Language :: Python :: 3.12
Classifier: Topic :: Communications :: Email
Classifier: Topic :: Software Development :: Libraries :: Python Modules
Requires-Python: >=3.10
Requires-Dist: pydantic>=2.5.0
Requires-Dist: superfunctions>=0.1.0
Provides-Extra: all
Requires-Dist: aioapns>=3.1.0; extra == 'all'
Requires-Dist: boto3>=1.34.0; extra == 'all'
Requires-Dist: firebase-admin>=6.5.0; extra == 'all'
Provides-Extra: dev
Requires-Dist: black>=23.11.0; extra == 'dev'
Requires-Dist: mypy>=1.7.0; extra == 'dev'
Requires-Dist: pytest-asyncio>=0.21.0; extra == 'dev'
Requires-Dist: pytest-cov>=4.1.0; extra == 'dev'
Requires-Dist: pytest>=7.4.0; extra == 'dev'
Requires-Dist: ruff>=0.1.6; extra == 'dev'
Requires-Dist: types-boto3>=1.0.0; extra == 'dev'
Provides-Extra: email
Requires-Dist: boto3>=1.34.0; extra == 'email'
Provides-Extra: fastapi
Requires-Dist: fastapi>=0.104.0; extra == 'fastapi'
Requires-Dist: superfunctions-fastapi>=0.1.0; extra == 'fastapi'
Provides-Extra: flask
Requires-Dist: flask>=3.0.0; extra == 'flask'
Requires-Dist: superfunctions-flask>=0.1.0; extra == 'flask'
Provides-Extra: push
Requires-Dist: aioapns>=3.1.0; extra == 'push'
Requires-Dist: firebase-admin>=6.5.0; extra == 'push'
Provides-Extra: sms
